Metadata-Version: 1.1
Name: MatrixOptimisation
Version: 2.0.3
Summary: Series of Functions Designed for Cellular Optimisation
Home-page: UNKNOWN
Author: Joshin Smith
Author-email: joshins@pepkor.co.za
License: MIT
Platform: UNKNOWN
Classifier: Development Status :: 5 - Production/Stable
Classifier: Natural Language :: English
